opsgenie_sdk/__init__.py
opsgenie_sdk/api_client.py
opsgenie_sdk/configuration.py
opsgenie_sdk/errors.py
opsgenie_sdk/exceptions.py
opsgenie_sdk/proxy_configuration.py
opsgenie_sdk/rest.py
opsgenie_sdk/api/__init__.py
opsgenie_sdk/api/account/__init__.py
opsgenie_sdk/api/account/account_info.py
opsgenie_sdk/api/account/account_plan.py
opsgenie_sdk/api/account/get_account_info_response.py
opsgenie_sdk/api/account/get_account_info_response_all_of.py
opsgenie_sdk/api/alert/__init__.py
opsgenie_sdk/api/alert/acknowledge_alert_payload.py
opsgenie_sdk/api/alert/add_details_to_alert_payload.py
opsgenie_sdk/api/alert/add_details_to_alert_payload_all_of.py
opsgenie_sdk/api/alert/add_note_to_alert_payload.py
opsgenie_sdk/api/alert/add_responder_to_alert_payload.py
opsgenie_sdk/api/alert/add_responder_to_alert_payload_all_of.py
opsgenie_sdk/api/alert/add_tags_to_alert_payload.py
opsgenie_sdk/api/alert/add_tags_to_alert_payload_all_of.py
opsgenie_sdk/api/alert/add_team_to_alert_payload.py
opsgenie_sdk/api/alert/add_team_to_alert_payload_all_of.py
opsgenie_sdk/api/alert/alert.py
opsgenie_sdk/api/alert/alert_action_payload.py
opsgenie_sdk/api/alert/alert_all_of.py
opsgenie_sdk/api/alert/alert_attachment.py
opsgenie_sdk/api/alert/alert_attachment_meta.py
opsgenie_sdk/api/alert/alert_integration.py
opsgenie_sdk/api/alert/alert_log.py
opsgenie_sdk/api/alert/alert_note.py
opsgenie_sdk/api/alert/alert_paging.py
opsgenie_sdk/api/alert/alert_recipient.py
opsgenie_sdk/api/alert/alert_report.py
opsgenie_sdk/api/alert/alert_request_status.py
opsgenie_sdk/api/alert/alert_team_meta.py
opsgenie_sdk/api/alert/alert_user_meta.py
opsgenie_sdk/api/alert/assign_alert_payload.py
opsgenie_sdk/api/alert/assign_alert_payload_all_of.py
opsgenie_sdk/api/alert/base_alert.py
opsgenie_sdk/api/alert/close_alert_payload.py
opsgenie_sdk/api/alert/create_alert_payload.py
opsgenie_sdk/api/alert/create_alert_payload_all_of.py
opsgenie_sdk/api/alert/create_saved_search_payload.py
opsgenie_sdk-2.1.4.dist-info/LICENSE.txt
opsgenie_sdk-2.1.4.dist-info/METADATA
opsgenie_sdk-2.1.4.dist-info/WHEEL
opsgenie_sdk-2.1.4.dist-info/top_level.txt
opsgenie_sdk-2.1.4.dist-info/RECORD
