Metadata-Version: 2.1
Name: opsgenie-sdk
Version: 2.1.4
Summary: Python SDK for Opsgenie REST API
Home-page: https://github.com/opsgenie/opsgenie-python-sdk
Author: OpsGenie
Author-email: support@opsgenie.com
License: UNKNOWN
Project-URL: Documentation, https://docs.opsgenie.com/docs/opsgenie-python-api
Project-URL: Source, https://github.com/opsgenie/opsgenie-python-sdk
Project-URL: Tracker, https://github.com/opsgenie/opsgenie-python-sdk/issues
Keywords: OpenAPI,OpenAPI-Generator,Python SDK for Opsgenie REST API,OpsGenie,Opsgenie
Platform: UNKNOWN
Classifier: Development Status :: 5 - Production/Stable
Classifier: License :: OSI Approved :: Apache Software License
Classifier: Operating System :: OS Independent
Requires-Dist: urllib3 (>=1.26.2)
Requires-Dist: six (>=1.10)
Requires-Dist: certifi
Requires-Dist: python-dateutil
Requires-Dist: setuptools (>=21.0.0)
Requires-Dist: tenacity (>=5.0.4)
